[
    {
        "Id": "0afb89d6f880a11e7a0c8ea8067721c9309a1c68b94d0b9ec943599bc6af1d14",
        "Created": "2017-12-02T20:39:28.297708067Z",
        "Path": "/bin/bash",
        "Args": [],
        "State": {
            "Status": "running",
            "Running": true,
            "Paused": false,
            "Restarting": false,
            "OOMKilled": false,
            "Dead": false,
            "Pid": 8011,
            "ExitCode": 0,
            "Error": "",
            "StartedAt": "2017-12-02T20:39:28.740728227Z",
            "FinishedAt": "0001-01-01T00:00:00Z"
        },
        "Image": "sha256:73abe3e083c56e24e703c527da48869218bc6ab2183a5fc39609008494dfb4a1",
        "ResolvConfPath": "/var/lib/docker/containers/0afb89d6f880a11e7a0c8ea8067721c9309a1c68b94d0b9ec943599bc6af1d14/resolv.conf",
        "HostnamePath": "/var/lib/docker/containers/0afb89d6f880a11e7a0c8ea8067721c9309a1c68b94d0b9ec943599bc6af1d14/hostname",
        "HostsPath": "/var/lib/docker/containers/0afb89d6f880a11e7a0c8ea8067721c9309a1c68b94d0b9ec943599bc6af1d14/hosts",
        "LogPath": "/var/lib/docker/containers/0afb89d6f880a11e7a0c8ea8067721c9309a1c68b94d0b9ec943599bc6af1d14/0afb89d6f880a11e7a0c8ea8067721c9309a1c68b94d0b9ec943599bc6af1d14-json.log",
        "Name": "/app_2_con",
        "RestartCount": 0,
        "Driver": "overlay2",
        "Platform": "linux",
        "MountLabel": "",
        "ProcessLabel": "",
        "AppArmorProfile": "docker-default",
        "ExecIDs": null,
        "HostConfig": {
            "Binds": null,
            "ContainerIDFile": "",
            "LogConfig": {
                "Type": "json-file",
                "Config": {}
            },
            "NetworkMode": "net_2",
            "PortBindings": {
                "80/tcp": [
                    {
                        "HostIp": "",
                        "HostPort": "5022"
                    }
                ]
            },
            "RestartPolicy": {
                "Name": "no",
                "MaximumRetryCount": 0
            },
            "AutoRemove": false,
            "VolumeDriver": "",
            "VolumesFrom": null,
            "CapAdd": null,
            "CapDrop": null,
            "Dns": [],
            "DnsOptions": [],
            "DnsSearch": [],
            "ExtraHosts": null,
            "GroupAdd": null,
            "IpcMode": "shareable",
            "Cgroup": "",
            "Links": null,
            "OomScoreAdj": 0,
            "PidMode": "",
            "Privileged": false,
            "PublishAllPorts": false,
            "ReadonlyRootfs": false,
            "SecurityOpt": null,
            "UTSMode": "",
            "UsernsMode": "",
            "ShmSize": 67108864,
            "Runtime": "runc",
            "ConsoleSize": [
                0,
                0
            ],
            "Isolation": "",
            "CpuShares": 0,
            "Memory": 0,
            "NanoCpus": 0,
            "CgroupParent": "",
            "BlkioWeight": 0,
            "BlkioWeightDevice": [],
            "BlkioDeviceReadBps": null,
            "BlkioDeviceWriteBps": null,
            "BlkioDeviceReadIOps": null,
            "BlkioDeviceWriteIOps": null,
            "CpuPeriod": 0,
            "CpuQuota": 0,
            "CpuRealtimePeriod": 0,
            "CpuRealtimeRuntime": 0,
            "CpusetCpus": "",
            "CpusetMems": "",
            "Devices": [],
            "DeviceCgroupRules": null,
            "DiskQuota": 0,
            "KernelMemory": 0,
            "MemoryReservation": 0,
            "MemorySwap": 0,
            "MemorySwappiness": null,
            "OomKillDisable": false,
            "PidsLimit": 0,
            "Ulimits": null,
            "CpuCount": 0,
            "CpuPercent": 0,
            "IOMaximumIOps": 0,
            "IOMaximumBandwidth": 0
        },
        "GraphDriver": {
            "Data": {
                ...
            },
            "Name": "overlay2"
        },
        "Mounts": [],
        "Config": {
            "Hostname": "0afb89d6f880",
            "Domainname": "",
            "User": "",
            "AttachStdin": false,
            "AttachStdout": false,
            "AttachStderr": false,
            "ExposedPorts": {
                "80/tcp": {}
            },
            "Tty": true,
            "OpenStdin": true,
            "StdinOnce": false,
            "Env": [
                "PATH=/usr/local/sbin:/usr/local/bin:/usr/sbin:/usr/bin:/sbin:/bin"
            ],
            "Cmd": [
                "/bin/bash"
            ],
            "ArgsEscaped": true,
            "Image": "app_2_img",
            "Volumes": null,
            "WorkingDir": "",
            "Entrypoint": null,
            "OnBuild": null,
            "Labels": {}
        },
        "NetworkSettings": {
            "Bridge": "",
            "SandboxID": "c3b8c5746ce389fc35268e1b5217f258a8ae1730061ee012c4bac97fa1b0a6f6",
            "HairpinMode": false,
            "LinkLocalIPv6Address": "",
            "LinkLocalIPv6PrefixLen": 0,
            "Ports": {
                "80/tcp": [
                    {
                        "HostIp": "0.0.0.0",
                        "HostPort": "5022"
                    }
                ]
            },
            "SandboxKey": "/var/run/docker/netns/c3b8c5746ce3",
            "SecondaryIPAddresses": null,
            "SecondaryIPv6Addresses": null,
            "EndpointID": "",
            "Gateway": "",
            "GlobalIPv6Address": "",
            "GlobalIPv6PrefixLen": 0,
            "IPAddress": "",
            "IPPrefixLen": 0,
            "IPv6Gateway": "",
            "MacAddress": "",
            "Networks": {
                "net_2": {
                    "IPAMConfig": {
                        "IPv4Address": "192.168.2.22"
                    },
                    "Links": null,
                    "Aliases": [
                        "0afb89d6f880"
                    ],
                    "NetworkID": "e8a8460784d0f67d2cac070c72e8e3153fed46453202825500908efa4cdcbffd",
                    "EndpointID": "17162311d44d53cbb9d3295ff3030b65b7f3dd1ef3bda116fd542af3d46b47fb",
                    "Gateway": "192.168.2.1",
                    "IPAddress": "192.168.2.22",
                    "IPPrefixLen": 24,
                    "IPv6Gateway": "",
                    "GlobalIPv6Address": "",
                    "GlobalIPv6PrefixLen": 0,
                    "MacAddress": "02:42:c0:a8:02:16",
                    "DriverOpts": null
                }
            }
        }
    }
]