{"birthday":"2017-11-30", "number_CC":"87654321", "first_rehearsal":"2017-12-31", "god_father":"","photo":"","vocal_range":"baixo","is_admin": "true" ,"accept_token":"null","phone":"123456789","naturality":"Montemor-o-Velho","name":"João Gonçalves","nickname":"gonçalves","course":"Jardinagem","subida":"1111-11-30","token_login":"58b9f58325265e06dce86a0a000495789fde3b11","position":"com_art","acepted_member": "true","id":"4","email":"joaogoncalves@mail.com","active_member":"true","statute":"quantunno"}